tima/__init__.py
tima/__main__.py
tima/tima_mindif_processor.py
tima/fonts/DejaVuSans.ttf
tima/fonts/DejaVuSansMono.ttf
tima_mindif-2.0.1.dist-info/LICENSE.txt
tima_mindif-2.0.1.dist-info/METADATA
tima_mindif-2.0.1.dist-info/WHEEL
tima_mindif-2.0.1.dist-info/entry_points.txt
tima_mindif-2.0.1.dist-info/top_level.txt
tima_mindif-2.0.1.dist-info/RECORD
