Metadata-Version: 2.1
Name: tima-mindif
Version: 2.0.1
Summary: TIMA Min Dif Processor
Home-page: https://gitlab.com/csiro-geoanalytics/tima-utils/tima-mindif-processor
Maintainer: Samuel Bradley
Maintainer-email: sam.bradley@csiro.au
License: MIT
Platform: UNKNOWN
Classifier: Development Status :: 4 - Beta
Classifier: Intended Audience :: Science/Research
Classifier: License :: OSI Approved :: MIT License
Classifier: Programming Language :: Python :: 3
Classifier: Programming Language :: Python :: 3.6
Classifier: Programming Language :: Python :: 3.7
Classifier: Programming Language :: Python :: 3.8
Requires-Python: >=3.5, <4
Requires-Dist: pillow (>=8.1.0)
Requires-Dist: loguru
Requires-Dist: numpy
